py_api_package/__init__.py
py_api_package/app.py
py_api_package/routes.py
flask_api_package-1.0.0.dist-info/METADATA
flask_api_package-1.0.0.dist-info/WHEEL
flask_api_package-1.0.0.dist-info/entry_points.txt
flask_api_package-1.0.0.dist-info/top_level.txt
flask_api_package-1.0.0.dist-info/RECORD
